[
  {"name": "token", "type": "function", "stateMutability": "view", "inputs": [], "outputs": [{"name": "", "type": "address"}]},
  {"name": "creator", "type": "function", "stateMutability": "view", "inputs": [], "outputs": [{"name": "", "type": "address"}]},
  {"name": "refund_to", "type": "function", "stateMutability": "view", "inputs": [], "outputs": [{"name": "", "type": "address"}]},
  {"name": "prompt", "type": "function", "stateMutability": "view", "inputs": [], "outputs": [{"name": "", "type": "string"}]},
  {"name": "max_amount", "type": "function", "stateMutability": "view", "inputs": [], "outputs": [{"name": "", "type": "uint256"}]},
  {"name": "floor_amount", "type": "function", "stateMutability": "view", "inputs": [], "outputs": [{"name": "", "type": "uint256"}]},
  {"name": "deadline", "type": "function", "stateMutability": "view", "inputs": [], "outputs": [{"name": "", "type": "uint256"}]},
  {"name": "max_shots", "type": "function", "stateMutability": "view", "inputs": [], "outputs": [{"name": "", "type": "uint256"}]},
  {"name": "curve_exponent", "type": "function", "stateMutability": "view", "inputs": [], "outputs": [{"name": "", "type": "uint256"}]},
  {"name": "answer_hash", "type": "function", "stateMutability": "view", "inputs": [], "outputs": [{"name": "", "type": "bytes32"}]},
  {"name": "funded", "type": "function", "stateMutability": "view", "inputs": [], "outputs": [{"name": "", "type": "bool"}]},
  {"name": "started", "type": "function", "stateMutability": "view", "inputs": [], "outputs": [{"name": "", "type": "bool"}]},
  {"name": "ended", "type": "function", "stateMutability": "view", "inputs": [], "outputs": [{"name": "", "type": "bool"}]},
  {"name": "start_time", "type": "function", "stateMutability": "view", "inputs": [], "outputs": [{"name": "", "type": "uint256"}]},
  {"name": "game_duration", "type": "function", "stateMutability": "view", "inputs": [], "outputs": [{"name": "", "type": "uint256"}]},
  {"name": "king", "type": "function", "stateMutability": "view", "inputs": [], "outputs": [{"name": "", "type": "address"}]},
  {"name": "king_since", "type": "function", "stateMutability": "view", "inputs": [], "outputs": [{"name": "", "type": "uint256"}]},
  {"name": "shot_sequence", "type": "function", "stateMutability": "view", "inputs": [], "outputs": [{"name": "", "type": "uint256"}]},
  {"name": "winner", "type": "function", "stateMutability": "view", "inputs": [], "outputs": [{"name": "", "type": "address"}]},
  {"name": "paid_amount", "type": "function", "stateMutability": "view", "inputs": [], "outputs": [{"name": "", "type": "uint256"}]},
  {"name": "clawed_back_amount", "type": "function", "stateMutability": "view", "inputs": [], "outputs": [{"name": "", "type": "uint256"}]},
  {"name": "king_prize", "type": "function", "stateMutability": "view", "inputs": [], "outputs": [{"name": "", "type": "uint256"}]},
  {"name": "prize_at", "type": "function", "stateMutability": "view", "inputs": [{"name": "_since", "type": "uint256"}, {"name": "_until", "type": "uint256"}], "outputs": [{"name": "", "type": "uint256"}]},
  {"name": "prize_for_hold_time", "type": "function", "stateMutability": "view", "inputs": [{"name": "_hold_time", "type": "uint256"}], "outputs": [{"name": "", "type": "uint256"}]},
  {"name": "shots_remaining", "type": "function", "stateMutability": "view", "inputs": [{"name": "_player", "type": "address"}], "outputs": [{"name": "", "type": "uint256"}]},
  {"name": "remaining_amount", "type": "function", "stateMutability": "view", "inputs": [], "outputs": [{"name": "", "type": "uint256"}]},
  {"name": "is_active", "type": "function", "stateMutability": "view", "inputs": [], "outputs": [{"name": "", "type": "bool"}]},
  {"name": "is_expired", "type": "function", "stateMutability": "view", "inputs": [], "outputs": [{"name": "", "type": "bool"}]},
  {"name": "is_ended", "type": "function", "stateMutability": "view", "inputs": [], "outputs": [{"name": "", "type": "bool"}]},
  {"name": "shoot", "type": "function", "stateMutability": "nonpayable", "inputs": [{"name": "_answer", "type": "string"}], "outputs": []},
  {"name": "fund", "type": "function", "stateMutability": "nonpayable", "inputs": [], "outputs": []},
  {"name": "start_game", "type": "function", "stateMutability": "nonpayable", "inputs": [], "outputs": []},
  {"name": "finalize", "type": "function", "stateMutability": "nonpayable", "inputs": [], "outputs": []},
  {"name": "clawback", "type": "function", "stateMutability": "nonpayable", "inputs": [], "outputs": []},
  {"name": "Funded", "type": "event", "inputs": [{"name": "creator", "type": "address", "indexed": true}, {"name": "amount", "type": "uint256", "indexed": false}]},
  {"name": "GameStarted", "type": "event", "inputs": [{"name": "start_time", "type": "uint256", "indexed": false}, {"name": "deadline", "type": "uint256", "indexed": false}]},
  {"name": "Shot", "type": "event", "inputs": [{"name": "player", "type": "address", "indexed": true}, {"name": "previous_king", "type": "address", "indexed": true}, {"name": "sequence", "type": "uint256", "indexed": false}, {"name": "shots_used", "type": "uint256", "indexed": false}, {"name": "captured_at", "type": "uint256", "indexed": false}]},
  {"name": "PrizePaid", "type": "event", "inputs": [{"name": "winner", "type": "address", "indexed": true}, {"name": "paid_amount", "type": "uint256", "indexed": false}, {"name": "remaining_amount", "type": "uint256", "indexed": false}]},
  {"name": "ClawedBack", "type": "event", "inputs": [{"name": "refund_to", "type": "address", "indexed": true}, {"name": "amount", "type": "uint256", "indexed": false}]},
  {"name": "GameEnded", "type": "event", "inputs": [{"name": "reason", "type": "uint256", "indexed": false}, {"name": "winner", "type": "address", "indexed": true}, {"name": "paid_amount", "type": "uint256", "indexed": false}, {"name": "clawed_back_amount", "type": "uint256", "indexed": false}]}
]
